qc_selector-0.1.3.dist-info/licenses/LICENSE
selector/__init__.py
selector/measures/__init__.py
selector/measures/converter.py
selector/measures/diversity.py
selector/measures/similarity.py
selector/measures/tests/__init__.py
selector/measures/tests/common.py
selector/measures/tests/test_converter.py
selector/measures/tests/test_diversity.py
selector/methods/__init__.py
selector/methods/base.py
selector/methods/distance.py
selector/methods/partition.py
selector/methods/similarity.py
selector/methods/utils.py
selector/methods/tests/__init__.py
selector/methods/tests/common.py
selector/methods/tests/test_distance.py
selector/methods/tests/test_partition.py
selector/methods/tests/test_similarity.py
selector/methods/tests/data/coords_imbalance_case1.txt
selector/methods/tests/data/coords_imbalance_case2.txt
selector/methods/tests/data/labels_imbalance_case1.txt
selector/methods/tests/data/labels_imbalance_case2.txt
selector/methods/tests/data/ref_esim_selection_data.csv
qc_selector-0.1.3.dist-info/METADATA
qc_selector-0.1.3.dist-info/WHEEL
qc_selector-0.1.3.dist-info/top_level.txt
qc_selector-0.1.3.dist-info/zip-safe
qc_selector-0.1.3.dist-info/RECORD
