Metadata-Version: 2.4
Name: qc-selector
Version: 0.1.3
Summary: Subset selection with maximum diversity.
Author-email: QC-Devs Community <qcdevs@gmail.com>
License:                     GNU GENERAL PUBLIC LICENSE
Project-URL: homepage, https://github.com/theochem/Selector
Project-URL: documentation, https://selector.qcdevs.org/
Project-URL: repository, https://github.com/theochem/Selector
Keywords: subset selection,variable selection,chemical diversity,compound selection,maximum diversity,chemical library design,compound acquisition
Platform: Linux
Platform: Windows
Platform: MacOS
Classifier: Development Status :: 5 - Production/Stable
Classifier: Environment :: Console
Classifier: License :: OSI Approved :: GNU General Public License v3 (GPLv3)
Classifier: Natural Language :: English
Classifier: Operating System :: MacOS
Classifier: Operating System :: Microsoft :: Windows
Classifier: Operating System :: Unix
Classifier: Operating System :: POSIX
Classifier: Operating System :: POSIX :: Linux
Classifier: Programming Language :: Python
Classifier: Programming Language :: Python :: 3
Classifier: Programming Language :: Python :: 3.9
Classifier: Programming Language :: Python :: 3.10
Classifier: Programming Language :: Python :: 3.11
Classifier: Programming Language :: Python :: 3.12
Classifier: Programming Language :: Python :: 3.13
Classifier: Topic :: Scientific/Engineering
Classifier: Topic :: Sociology
Requires-Python: >=3.9
License-File: LICENSE
Requires-Dist: bitarray>=2.5.1
Requires-Dist: numpy>=1.21.2
Requires-Dist: scipy>=1.11.1
Provides-Extra: dev
Requires-Dist: bitarray>=2.5.1; extra == "dev"
Requires-Dist: coverage>=6.3.2; extra == "dev"
Requires-Dist: hypothesis; extra == "dev"
Requires-Dist: numpy>=1.21.2; extra == "dev"
Requires-Dist: pre-commit; extra == "dev"
Requires-Dist: pytest>=7.4.0; extra == "dev"
Requires-Dist: pytest-cov>=3.0.0; extra == "dev"
Requires-Dist: scikit-learn>=1.0.1; extra == "dev"
Requires-Dist: scipy>=1.11.1; extra == "dev"
Requires-Dist: setuptools>=64.0.0; extra == "dev"
Requires-Dist: tomli; extra == "dev"
Requires-Dist: xdoctest; extra == "dev"
Requires-Dist: setuptools-scm>=8.0.0; extra == "dev"
Dynamic: license-file
